README.md
setup.py
src/lgplibdemo/__init__.py
src/lgplibdemo/lgpdemo.py
src/lgplibdemo/lgplib.py
src/lgplibdemo.egg-info/PKG-INFO
src/lgplibdemo.egg-info/SOURCES.txt
src/lgplibdemo.egg-info/dependency_links.txt
src/lgplibdemo.egg-info/top_level.txt