Metadata-Version: 1.2
Name: lgplibdemo
Version: 0.0.2
Summary: library for Robot Framework
Home-page: https://github.com/ligaopan/lgp-library
Author: ligaopan
Author-email: ligaopan1984@163.com
License: MIT Licence
Keywords: robotframework testing testautomation
Platform: any
Requires-Python: >=3.7.*
